stellarobservatory/__init__.py
stellarobservatory/centralities.py
stellarobservatory/centralities_test.py
stellarobservatory/dsets.py
stellarobservatory/dsets_test.py
stellarobservatory/intactness.py
stellarobservatory/intactness_test.py
stellarobservatory/nodes.py
stellarobservatory/nodes_test.py
stellarobservatory/quorum.py
stellarobservatory/quorum_intersection.py
stellarobservatory/quorum_intersection_test.py
stellarobservatory/quorum_slice_definition.py
stellarobservatory/quorum_slice_definition_test.py
stellarobservatory/quorum_slices.py
stellarobservatory/quorum_slices_test.py
stellarobservatory/quorum_test.py
stellarobservatory/quorums.py
stellarobservatory/quorums_test.py
stellarobservatory/stellarbeat.py
stellarobservatory/stellarbeat_test.py
stellarobservatory/utils/__init__.py
stellarobservatory/utils/graph.py
stellarobservatory/utils/graph_test.py
stellarobservatory/utils/hypergraph.py
stellarobservatory/utils/scc.py
stellarobservatory/utils/scc_test.py
stellarobservatory/utils/sets.py
stellarobservatory/utils/sets_test.py
stellar_observatory-1.0.1.dist-info/LICENSE
stellar_observatory-1.0.1.dist-info/METADATA
stellar_observatory-1.0.1.dist-info/WHEEL
stellar_observatory-1.0.1.dist-info/top_level.txt
stellar_observatory-1.0.1.dist-info/RECORD
