Metadata-Version: 2.1
Name: stellar-observatory
Version: 1.0.1
Summary: Python package for analyzing the Stellar network
Home-page: https://github.com/andrenarchy/stellar-observatory
Author: André Gaul
Author-email: andre@gaul.io
License: UNKNOWN
Platform: UNKNOWN
Classifier: Programming Language :: Python :: 3
Classifier: License :: OSI Approved :: MIT License
Classifier: Operating System :: OS Independent
Classifier: Intended Audience :: Science/Research
Requires-Python: ~=3.5
